adafruit_tlv320.py
adafruit_circuitpython_tlv320-1.3.0.dist-info/licenses/LICENSE
adafruit_circuitpython_tlv320-1.3.0.dist-info/METADATA
adafruit_circuitpython_tlv320-1.3.0.dist-info/WHEEL
adafruit_circuitpython_tlv320-1.3.0.dist-info/top_level.txt
adafruit_circuitpython_tlv320-1.3.0.dist-info/RECORD
