Metadata-Version: 2.4
Name: adafruit-circuitpython-tlv320
Version: 1.3.0
Summary: CircuitPython driver for the TLV320DAC3100 I2S DAC
Author-email: Adafruit Industries <circuitpython@adafruit.com>
License: MIT
Project-URL: Homepage, https://github.com/adafruit/Adafruit_CircuitPython_TLV320
Keywords: adafruit,blinka,circuitpython,micropython,tlv320,I2S,,DAC,,TLV320DAC3100
Classifier: Intended Audience :: Developers
Classifier: Topic :: Software Development :: Libraries
Classifier: Topic :: Software Development :: Embedded Systems
Classifier: Topic :: System :: Hardware
Classifier: License :: OSI Approved :: MIT License
Classifier: Programming Language :: Python :: 3
License-File: LICENSE
Requires-Dist: Adafruit-Blinka
Requires-Dist: adafruit-circuitpython-busdevice
Provides-Extra: optional
Dynamic: license-file
